psycopg_binary-3.2.11.dist-info/RECORD
psycopg_binary-3.2.11.dist-info/WHEEL
psycopg_binary-3.2.11.dist-info/top_level.txt
psycopg_binary-3.2.11.dist-info/METADATA
psycopg_binary-3.2.11.dist-info/licenses/LICENSE.txt
psycopg_binary/_uuid.py
psycopg_binary/_psycopg.pyi
psycopg_binary/version.py
psycopg_binary/_psycopg.cpython-314-darwin.so
psycopg_binary/pq.cpython-314-darwin.so
psycopg_binary/__init__.py
psycopg_binary/py.typed
psycopg_binary/.dylibs/libcom_err.3.0.dylib
psycopg_binary/.dylibs/libldap.2.dylib
psycopg_binary/.dylibs/libpq.5.dylib
psycopg_binary/.dylibs/libsasl2.3.dylib
psycopg_binary/.dylibs/libssl.3.dylib
psycopg_binary/.dylibs/libcrypto.3.dylib
psycopg_binary/.dylibs/libgssapi_krb5.2.2.dylib
psycopg_binary/.dylibs/liblber.2.dylib
psycopg_binary/.dylibs/libkrb5.3.3.dylib
psycopg_binary/.dylibs/libkrb5support.1.1.dylib
psycopg_binary/.dylibs/libk5crypto.3.1.dylib
