Metadata-Version: 2.1
Name: psycopg-binary
Version: 3.2.11
Summary: PostgreSQL database adapter for Python -- C optimisation distribution
Home-page: https://psycopg.org/psycopg3/
Author: Daniele Varrazzo
Author-email: daniele.varrazzo@gmail.com
Project-URL: Homepage, https://psycopg.org/
Project-URL: Documentation, https://psycopg.org/psycopg3/docs/
Project-URL: Changes, https://psycopg.org/psycopg3/docs/news.html
Project-URL: Code, https://github.com/psycopg/psycopg
Project-URL: Issue Tracker, https://github.com/psycopg/psycopg/issues
Project-URL: Download, https://pypi.org/project/psycopg-binary/
Project-URL: Funding, https://github.com/sponsors/dvarrazzo
Classifier: Development Status :: 5 - Production/Stable
Classifier: Intended Audience :: Developers
Classifier: Operating System :: MacOS :: MacOS X
Classifier: Operating System :: Microsoft :: Windows
Classifier: Operating System :: POSIX
Classifier: Programming Language :: Cython
Classifier: Programming Language :: Python :: 3
Classifier: Programming Language :: Python :: 3.8
Classifier: Programming Language :: Python :: 3.9
Classifier: Programming Language :: Python :: 3.10
Classifier: Programming Language :: Python :: 3.11
Classifier: Programming Language :: Python :: 3.12
Classifier: Programming Language :: Python :: 3.13
Classifier: Programming Language :: Python :: 3.14
Classifier: Programming Language :: Python :: Implementation :: CPython
Classifier: Topic :: Database
Classifier: Topic :: Database :: Front-Ends
Classifier: Topic :: Software Development
Classifier: Topic :: Software Development :: Libraries :: Python Modules
Requires-Python: >=3.8
License-File: LICENSE.txt
